setup.py
distributions_binomial_gaussian_786/Binomialdistribution.py
distributions_binomial_gaussian_786/Gaussiandistribution.py
distributions_binomial_gaussian_786/Generaldistribution.py
distributions_binomial_gaussian_786/__init__.py
distributions_binomial_gaussian_786.egg-info/PKG-INFO
distributions_binomial_gaussian_786.egg-info/SOURCES.txt
distributions_binomial_gaussian_786.egg-info/dependency_links.txt
distributions_binomial_gaussian_786.egg-info/not-zip-safe
distributions_binomial_gaussian_786.egg-info/top_level.txt