Metadata-Version: 1.0
Name: distributions-binomial-gaussian-786
Version: 0.5
Summary: Gaussian and Binomial distributions
Home-page: UNKNOWN
Author: A7MED
Author-email: waqasne@gmail.com
License: UNKNOWN
Platform: UNKNOWN
